redis_namespace_client/__init__.py
redis_namespace_client/redis_utils.py
redis_namespace_client-0.1.2.dist-info/licenses/LICENSE
redis_namespace_client-0.1.2.dist-info/METADATA
redis_namespace_client-0.1.2.dist-info/WHEEL
redis_namespace_client-0.1.2.dist-info/top_level.txt
redis_namespace_client-0.1.2.dist-info/RECORD
