Metadata-Version: 2.4
Name: redis-namespace-client
Version: 0.1.2
Summary: A simple Redis client for Python with support for: namespacing and JSON serialization/deserialization, designed for middleware applications.
Home-page: https://github.com/cloudtechy/redis-namespace-client
Download-URL: https://github.com/cloudtechy/redis-namespace-client/archive/refs/tags/0.1.2.tar.gz
Author: Onyekelu Chukwuebuka
Author-email: Onyekelu Chukwuebuka <conyekelu@yahoo.com>
License: MIT
Requires-Python: >=3.7
License-File: LICENSE
Requires-Dist: requests
Requires-Dist: python-dotenv
Requires-Dist: redis
Requires-Dist: urllib3
Dynamic: author
Dynamic: download-url
Dynamic: home-page
Dynamic: license-file
Dynamic: requires-python
